{
 "HRDK-L-0598": {
  "cls": "현상 유지",
  "law": "주차장법 시행령",
  "date": "20250817",
  "rel": "단순관련",
  "row": 12
 },
 "HRDK-L-1088": {
  "cls": "현상 유지",
  "law": "중소기업기본법 시행령",
  "date": "20260102",
  "rel": "단순관련",
  "row": 501
 },
 "HRDK-L-1091": {
  "cls": "현상 유지",
  "law": "지방자치단체를 당사자로 하는 계약에 관한 법률 시행령",
  "date": "20260102",
  "rel": "단순관련",
  "row": 504
 },
 "HRDK-L-1094": {
  "cls": "현상 유지",
  "law": "한국전력공사법",
  "date": "20260102",
  "rel": "단순관련",
  "row": 507
 },
 "HRDK-L-1142": {
  "cls": "현상 유지",
  "law": "주택건설기준 등에 관한 규칙",
  "date": "20260130",
  "rel": "연관높음",
  "row": 570
 },
 "HRDK-L-1217": {
  "cls": "현상 유지",
  "law": "한국산업안전보건공단법",
  "date": "20260212",
  "rel": "단순관련",
  "row": 681
 },
 "HRDK-L-1291": {
  "cls": "현상 유지",
  "law": "부패재산의 몰수 및 회복에 관한 특례법",
  "date": "20260306",
  "rel": "단순관련",
  "row": 772
 },
 "HRDK-L-1340": {
  "cls": "소폭 증가",
  "law": "군인보수법",
  "date": "20260319",
  "rel": "단순관련",
  "row": 839
 },
 "HRDK-L-1428": {
  "cls": "현상 유지",
  "law": "산업교육진흥 및 산학연협력촉진에 관한 법률 시행령",
  "date": "20260324",
  "rel": "단순관련",
  "row": 974
 },
 "HRDK-L-1434": {
  "cls": "소폭 증가",
  "law": "축산법 시행규칙",
  "date": "20260324",
  "rel": "단순관련",
  "row": 980
 },
 "HRDK-L-1505": {
  "cls": "현상 유지",
  "law": "사회복지공동모금회법",
  "date": "20260331",
  "rel": "단순관련",
  "row": 1069
 },
 "HRDK-L-1506": {
  "cls": "소폭 증가",
  "law": "지방공기업법 시행령",
  "date": "20260331",
  "rel": "단순관련",
  "row": 1070
 },
 "HRDK-L-1540": {
  "cls": "현상 유지",
  "law": "선박직원법 시행규칙",
  "date": "20260409",
  "rel": "단순관련",
  "row": 1111
 },
 "HRDK-L-1675": {
  "cls": "소폭 증가",
  "law": "공익사업을 위한 토지 등의 취득 및 보상에 관한 법률 시행령",
  "date": "20260512",
  "rel": "단순관련",
  "row": 1281
 },
 "HRDK-L-1845": {
  "cls": "현상 유지",
  "law": "수도법 시행령",
  "date": "20260603",
  "rel": "단순관련",
  "row": 1486
 },
 "HRDK-L-1848": {
  "cls": "현상 유지",
  "law": "중소기업협동조합법 시행령",
  "date": "20260603",
  "rel": "단순관련",
  "row": 1489
 },
 "HRDK-L-1850": {
  "cls": "현상 유지",
  "law": "화물자동차 운수사업법 시행령",
  "date": "20260603",
  "rel": "단순관련",
  "row": 1491
 },
 "HRDK-L-1857": {
  "cls": "현상 유지",
  "law": "공익사업을 위한 토지 등의 취득 및 보상에 관한 법률",
  "date": "20260616",
  "rel": "단순관련",
  "row": 1507
 },
 "HRDK-L-1858": {
  "cls": "소폭 증가",
  "law": "농업인등의 농외소득 활동 지원에 관한 법률",
  "date": "20260616",
  "rel": "단순관련",
  "row": 1508
 },
 "HRDK-L-1860": {
  "cls": "현상 유지",
  "law": "디자인보호법 시행규칙",
  "date": "20260617",
  "rel": "단순관련",
  "row": 1512
 },
 "HRDK-L-1861": {
  "cls": "현상 유지",
  "law": "농어업경영체 육성 및 지원에 관한 법률 시행규칙",
  "date": "20260618",
  "rel": "단순관련",
  "row": 1515
 },
 "HRDK-L-1862": {
  "cls": "현상 유지",
  "law": "약사법",
  "date": "20260621",
  "rel": "단순관련",
  "row": 1516
 },
 "HRDK-L-1866": {
  "cls": "현상 유지",
  "law": "공공주택 특별법 시행규칙",
  "date": "20260622",
  "rel": "단순관련",
  "row": 1534
 },
 "HRDK-L-1867": {
  "cls": "현상 유지",
  "law": "소음ㆍ진동관리법 시행규칙",
  "date": "20260622",
  "rel": "단순관련",
  "row": 1535
 },
 "HRDK-L-1868": {
  "cls": "소폭 증가",
  "law": "전기ㆍ전자제품 및 자동차의 자원순환에 관한 법률 시행규칙",
  "date": "20260622",
  "rel": "단순관련",
  "row": 1536
 },
 "HRDK-L-1869": {
  "cls": "현상 유지",
  "law": "지하수법 시행규칙",
  "date": "20260622",
  "rel": "단순관련",
  "row": 1537
 },
 "HRDK-L-1873": {
  "cls": "현상 유지",
  "law": "경제안보를 위한 공급망 안정화 지원 기본법 시행령",
  "date": "20260624",
  "rel": "단순관련",
  "row": 1546
 },
 "HRDK-L-0608": {
  "cls": "현상 유지",
  "law": "지방공무원 임용령",
  "date": "20260630",
  "rel": "연관높음",
  "row": 1553
 },
 "HRDK-L-1879": {
  "cls": "현상 유지",
  "law": "공무원임용령",
  "date": "20260630",
  "rel": "단순관련",
  "row": 1559
 },
 "HRDK-L-1880": {
  "cls": "소폭 증가",
  "law": "빈집 및 소규모주택 정비에 관한 특례법 시행령",
  "date": "20260630",
  "rel": "단순관련",
  "row": 1560
 },
 "HRDK-L-1881": {
  "cls": "현상 유지",
  "law": "연구직 및 지도직공무원의 임용 등에 관한 규정",
  "date": "20260630",
  "rel": "단순관련",
  "row": 1561
 },
 "HRDK-L-1882": {
  "cls": "소폭 증가",
  "law": "전문직공무원 인사규정",
  "date": "20260630",
  "rel": "단순관련",
  "row": 1562
 },
 "HRDK-L-1883": {
  "cls": "현상 유지",
  "law": "항공안전법 시행령",
  "date": "20260630",
  "rel": "단순관련",
  "row": 1563
 },
 "HRDK-L-0205": {
  "cls": "현상 유지",
  "law": "공무원임용령",
  "date": "20260701",
  "rel": "단순관련",
  "row": 1573
 },
 "HRDK-L-0700": {
  "cls": "현상 유지",
  "law": "영산강ㆍ섬진강수계 물관리 및 주민지원 등에 관한 법률",
  "date": "20260701",
  "rel": "단순관련",
  "row": 1606
 },
 "HRDK-L-0701": {
  "cls": "소폭 증가",
  "law": "의용소방대 설치 및 운영에 관한 법률 시행규칙",
  "date": "20260701",
  "rel": "단순관련",
  "row": 1607
 },
 "HRDK-L-0704": {
  "cls": "현상 유지",
  "law": "지방세법 시행규칙",
  "date": "20260701",
  "rel": "단순관련",
  "row": 1610
 },
 "HRDK-L-1955": {
  "cls": "현상 유지",
  "law": "119구조ㆍ구급에 관한 법률 시행규칙",
  "date": "20260701",
  "rel": "단순관련",
  "row": 1684
 },
 "HRDK-L-1956": {
  "cls": "현상 유지",
  "law": "119긴급신고의 관리 및 운영에 관한 법률 시행규칙",
  "date": "20260701",
  "rel": "단순관련",
  "row": 1685
 },
 "HRDK-L-1957": {
  "cls": "소폭 증가",
  "law": "12ㆍ29여객기참사 피해구제 및 지원 등을 위한 특별법",
  "date": "20260701",
  "rel": "단순관련",
  "row": 1686
 },
 "HRDK-L-1958": {
  "cls": "소폭 증가",
  "law": "국유재산법 시행령",
  "date": "20260701",
  "rel": "단순관련",
  "row": 1687
 },
 "HRDK-L-1959": {
  "cls": "현상 유지",
  "law": "군사기지 및 군사시설 보호법 시행령",
  "date": "20260701",
  "rel": "단순관련",
  "row": 1688
 },
 "HRDK-L-1960": {
  "cls": "소폭 증가",
  "law": "규제자유특구 및 지역특화발전특구에 관한 규제특례법 시행령",
  "date": "20260701",
  "rel": "단순관련",
  "row": 1689
 },
 "HRDK-L-1961": {
  "cls": "현상 유지",
  "law": "긴급구조대응활동 및 현장지휘에 관한 규칙",
  "date": "20260701",
  "rel": "단순관련",
  "row": 1690
 },
 "HRDK-L-1962": {
  "cls": "현상 유지",
  "law": "농업ㆍ농촌 및 식품산업 기본법",
  "date": "20260701",
  "rel": "단순관련",
  "row": 1691
 },
 "HRDK-L-1963": {
  "cls": "소폭 증가",
  "law": "농업ㆍ농촌 및 식품산업 기본법 시행령",
  "date": "20260701",
  "rel": "단순관련",
  "row": 1692
 },
 "HRDK-L-1964": {
  "cls": "현상 유지",
  "law": "도시 및 주거환경정비법",
  "date": "20260701",
  "rel": "단순관련",
  "row": 1693
 },
 "HRDK-L-1965": {
  "cls": "현상 유지",
  "law": "도심 복합개발 지원에 관한 법률 시행령",
  "date": "20260701",
  "rel": "단순관련",
  "row": 1694
 },
 "HRDK-L-1966": {
  "cls": "소폭 증가",
  "law": "도심융합특구 조성 및 육성에 관한 특별법",
  "date": "20260701",
  "rel": "단순관련",
  "row": 1695
 },
 "HRDK-L-1967": {
  "cls": "현상 유지",
  "law": "도심융합특구 조성 및 육성에 관한 특별법 시행령",
  "date": "20260701",
  "rel": "단순관련",
  "row": 1696
 },
 "HRDK-L-1968": {
  "cls": "소폭 증가",
  "law": "동ㆍ서ㆍ남해안 및 내륙권 발전 특별법 시행령",
  "date": "20260701",
  "rel": "단순관련",
  "row": 1697
 },
 "HRDK-L-1969": {
  "cls": "현상 유지",
  "law": "방문판매 등에 관한 법률 시행령",
  "date": "20260701",
  "rel": "단순관련",
  "row": 1698
 },
 "HRDK-L-1970": {
  "cls": "현상 유지",
  "law": "방위사업법 시행규칙",
  "date": "20260701",
  "rel": "단순관련",
  "row": 1699
 },
 "HRDK-L-1971": {
  "cls": "소폭 증가",
  "law": "산업 디지털 전환 및 인공지능 활용 촉진법 시행령",
  "date": "20260701",
  "rel": "단순관련",
  "row": 1700
 },
 "HRDK-L-1972": {
  "cls": "현상 유지",
  "law": "산업재해보상보험법",
  "date": "20260701",
  "rel": "단순관련",
  "row": 1701
 },
 "HRDK-L-1973": {
  "cls": "현상 유지",
  "law": "소득세법 시행령",
  "date": "20260701",
  "rel": "단순관련",
  "row": 1702
 },
 "HRDK-L-1974": {
  "cls": "소폭 증가",
  "law": "소상공인 보호 및 지원에 관한 법률",
  "date": "20260701",
  "rel": "단순관련",
  "row": 1703
 },
 "HRDK-L-1975": {
  "cls": "현상 유지",
  "law": "어선안전조업 및 어선원의 안전ㆍ보건 증진 등에 관한 법률",
  "date": "20260701",
  "rel": "단순관련",
  "row": 1704
 },
 "HRDK-L-1976": {
  "cls": "현상 유지",
  "law": "어선안전조업 및 어선원의 안전ㆍ보건 증진 등에 관한 법률 시행규칙",
  "date": "20260701",
  "rel": "단순관련",
  "row": 1705
 },
 "HRDK-L-1977": {
  "cls": "현상 유지",
  "law": "어촌ㆍ어항법 시행령",
  "date": "20260701",
  "rel": "단순관련",
  "row": 1706
 },
 "HRDK-L-1978": {
  "cls": "현상 유지",
  "law": "원자력안전 정보공개 및 소통에 관한 법률 시행령",
  "date": "20260701",
  "rel": "단순관련",
  "row": 1707
 },
 "HRDK-L-1979": {
  "cls": "현상 유지",
  "law": "의료기기법 시행령",
  "date": "20260701",
  "rel": "단순관련",
  "row": 1708
 },
 "HRDK-L-1980": {
  "cls": "현상 유지",
  "law": "장애인고용촉진 및 직업재활법 시행규칙",
  "date": "20260701",
  "rel": "단순관련",
  "row": 1709
 },
 "HRDK-L-1981": {
  "cls": "소폭 증가",
  "law": "전남광주통합특별시 설치를 위한 특별법 시행령",
  "date": "20260701",
  "rel": "단순관련",
  "row": 1710
 },
 "HRDK-L-1982": {
  "cls": "현상 유지",
  "law": "제주특별자치도 설치 및 국제자유도시 조성을 위한 특별법",
  "date": "20260701",
  "rel": "단순관련",
  "row": 1711
 },
 "HRDK-L-1983": {
  "cls": "소폭 증가",
  "law": "주류 면허 등에 관한 법률 시행령",
  "date": "20260701",
  "rel": "단순관련",
  "row": 1712
 },
 "HRDK-L-1984": {
  "cls": "현상 유지",
  "law": "책임운영기관의 설치ㆍ운영에 관한 법률 시행령",
  "date": "20260701",
  "rel": "단순관련",
  "row": 1713
 },
 "HRDK-L-1985": {
  "cls": "소폭 증가",
  "law": "청소년복지 지원법",
  "date": "20260701",
  "rel": "단순관련",
  "row": 1714
 },
 "HRDK-L-1986": {
  "cls": "현상 유지",
  "law": "초고층 및 지하연계 복합건축물 재난관리에 관한 특별법 시행규칙",
  "date": "20260701",
  "rel": "단순관련",
  "row": 1715
 },
 "HRDK-L-1987": {
  "cls": "현상 유지",
  "law": "표시ㆍ광고의 공정화에 관한 법률 시행령",
  "date": "20260701",
  "rel": "단순관련",
  "row": 1716
 },
 "HRDK-L-1988": {
  "cls": "현상 유지",
  "law": "하천법 시행령",
  "date": "20260701",
  "rel": "단순관련",
  "row": 1717
 },
 "HRDK-L-1989": {
  "cls": "현상 유지",
  "law": "할부거래에 관한 법률 시행령",
  "date": "20260701",
  "rel": "단순관련",
  "row": 1718
 },
 "HRDK-L-1990": {
  "cls": "현상 유지",
  "law": "항공안전법 시행령",
  "date": "20260701",
  "rel": "단순관련",
  "row": 1719
 }
}